{
    "@odata.type": "#ietf_system.system.dns_resolver.server.v1_0_0.server",
    "Id": "server1",
    "Name": "dns_resolver server",
    "name": "dan_resolver server",
    "udp_and_tcp": {
        "address": "192.168.1.56",
        "port": "53"
    },
    "@odata.context": "/redfish/v1/$metadata#ietf_system.system.dns_resolver.dns_resolver.server.server",
    "@odata.id": "/redfish/v1/NetworkDevices/SW_15/ietf_system/system/dns_resolver/server/server1",
    "@Redfish.Copyright": "Copyright 2014-2017 Distributed Management Task Force, Inc. (DMTF). For the full DMTF copyright policy, see http://www.dmtf.org/about/policies/copyright."
}
