{
  "@Redfish.Copyright": "Copyright 2016 Distributed Management Task Force, Inc. (DMTF). All rights reserved.",
  "@odata.context": "/redfish/v1/$metadata#Systems/Members/1/BootOptions/Members/$entity",
  "@odata.id": "/redfish/v1/Systems/1/BootOptions/4",
  "@odata.type": "#BootOption.v1_0_0.BootOption",
  "Name": "Boot Option",
  "Id": "4",
  "Description": "UEFI Boot Option",  
  "BootId": "Boot0003",
  "UefiDevicePath": "PciRoot(0x0)/Pci(0x1C,0x4)/Pci(0x0,0x0)/MAC(0002B3AFE1D8,0x0)/IPv4(0.0.0.0)",
  "BootDescription": "NIC 1 PXE Boot - IPv4",
  "Alias": "Pxe",
  "RelatedItem": [
    { "@odata.id": "/redfish/v1/Chassis/1/NetworkAdapters/9fd725a1/" }
  ],
  "Oem": { }
}
