{
    "@Redfish.Copyright": "Copyright 2014-2019 DMTF. All rights reserved.",
    "@odata.context": "/redfish/v1/$metadata#ZoneCollection.ZoneCollection",
    "@odata.id": "/redfish/v1/Fabrics/ComplexPCIe/Zones",
    "@odata.type": "#ZoneCollection.ZoneCollection",
    "Name": "PCIe Zone Collection",
    "Members@odata.count": 4,
    "Members": [
        {
            "@odata.id": "/redfish/v1/Fabrics/ComplexPCIe/Zones/1"
        },
        {
            "@odata.id": "/redfish/v1/Fabrics/ComplexPCIe/Zones/2"
        },
        {
            "@odata.id": "/redfish/v1/Fabrics/ComplexPCIe/Zones/3"
        },
        {
            "@odata.id": "/redfish/v1/Fabrics/ComplexPCIe/Zones/4"
        }
    ]
}

